deploydb/__init__.py
deploydb/base.py
deploydb/db.py
deploydb/listener.py
deploydb/model.py
deploydb/repo_generator.py
deploydb/script.py
deploydb/utils.py
deploydb-0.2.3.dist-info/LICENSE
deploydb-0.2.3.dist-info/METADATA
deploydb-0.2.3.dist-info/WHEEL
deploydb-0.2.3.dist-info/top_level.txt
deploydb-0.2.3.dist-info/RECORD
