Metadata-Version: 2.1
Name: deploydb
Version: 0.2.3
Summary: Deploy your database objects automatically when the git branch is updated.
Home-page: https://github.com/mertguvencli/deploydb
Author: Mert Güvençli
Author-email: guvenclimert@gmail.com
License: GNU General Public License v3
Keywords: deploydb,sql server,source control,deployment
Platform: UNKNOWN
Classifier: Development Status :: 5 - Production/Stable
Classifier: Intended Audience :: Developers
Classifier: License :: OSI Approved :: GNU General Public License v3 (GPLv3)
Classifier: Natural Language :: English
Classifier: Programming Language :: Python :: 3
Classifier: Programming Language :: Python :: 3.6
Classifier: Programming Language :: Python :: 3.7
Classifier: Programming Language :: Python :: 3.8
Requires-Python: >=3.6
Requires-Dist: pyodbc
Requires-Dist: GitPython
Requires-Dist: pydantic
Requires-Dist: tqdm
